{"copiesArrays": true, "copiesArrayObjects": true, "nodeDataArray": [{"key": 0, "type": "Table", "question": "右耳優位性", "actions": [{"text": "", "figure": "Hammer"}, {"text": "数字・有意味語・言語音なの言語刺激を呈示した場合には", "figure": "Caution"}, {"text": "一般 に右耳優位性がみられることを確認している。", "figure": "BpmnTaskMessage"}], "example": "数字・有意味語・言語音なの言語刺激を呈示した場合には,一般 に右耳優位性がみられることを確認している。", "effect": "右", "method": "", "file_path": "/blog/blog/9100certification/1100_keywords_1000.md", "page_url": "https://psy.hatenadiary.com/entry/2025/04/18/191338"}, {"key": 1, "type": "Table", "question": "言語化", "actions": [{"text": "", "figure": "Hammer"}, {"text": "言語化しやすい色ほど、記憶が定着しやすい", "figure": "Hammer"}], "example": "言語化しやすい色ほど、記憶が定着しやすい", "effect": "定着", "method": "", "file_path": "/blog/blog/9100certification/1100_keywords_1000.md", "page_url": "https://psy.hatenadiary.com/entry/2025/04/18/191338"}, {"key": 2, "type": "Table", "question": "ノスタルジア", "actions": [{"text": "", "figure": "Hammer"}, {"text": "「ノスタルジアは自己の連続性（＝過去と今と未来の自分を一体と感じること）を強め、困難な状況においても希望を持たせる」効果がある", "figure": "BpmnTaskMessage"}], "example": "「ノスタルジアは自己の連続性（＝過去と今と未来の自分を一体と感じること）を強め、困難な状況においても希望を持たせる」効果がある", "effect": "未来", "method": "", "file_path": "/blog/blog/9100certification/1100_keywords_1000.md", "page_url": "https://psy.hatenadiary.com/entry/2025/04/18/191338"}, {"key": 3, "type": "Table", "question": "レミニセンスバンプ", "actions": [{"text": "", "figure": "BpmnTaskMessage"}, {"text": "伝的記憶は、自身が10-20代の頃の記憶が多く想起される傾向がある", "figure": "Hammer"}], "example": "伝的記憶は、自身が10-20代の頃の記憶が多く想起される傾向がある", "effect": "10代から20代", "method": "", "file_path": "/blog/blog/9100certification/1100_keywords_1000.md", "page_url": "https://psy.hatenadiary.com/entry/2025/04/18/191338"}, {"key": 4, "type": "Table", "question": "般化", "actions": [{"text": "", "figure": "BpmnTaskMessage"}, {"text": "ある色の信号機に反応するようになったら、少し色違いの信号機にも同じ反応を示す。", "figure": "Hammer"}, {"text": "犬を「ワン」と呼ぶ言葉を習得したら、他の犬にも「ワン」と呼ぶ。", "figure": "Hammer"}], "example": "ある色の信号機に反応するようになったら、少し色違いの信号機にも同じ反応を示す。,犬を「ワン」と呼ぶ言葉を習得したら、他の犬にも「ワン」と呼ぶ。", "effect": "応用力", "method": "", "file_path": "/blog/blog/9100certification/1100_keywords_1000.md", "page_url": "https://psy.hatenadiary.com/entry/2025/04/18/191338"}, {"key": 5, "type": "Table", "question": "即座の満足", "actions": [{"text": "", "figure": "Caution"}, {"text": "人間は即時の満足を優先する傾向があり、これを「時間割引」と呼びます。", "figure": "BpmnTaskMessage"}], "example": "人間は即時の満足を優先する傾向があり、これを「時間割引」と呼びます。", "effect": "評価する", "method": "", "file_path": "/blog/blog/0000HUMAN/20250420222349lent_money.md", "page_url": "https://psy.hatenadiary.com/entry/2025/04/22/160955"}, {"key": 6, "type": "Table", "question": "ほしいもの", "actions": [{"text": "", "figure": "BpmnTaskMessage"}, {"text": "チョコレートマフィンの大きさを訪ねる実験をしたところ、ダイエットをしている人間の方が大きいと判断した。", "figure": "Hammer"}], "example": "チョコレートマフィンの大きさを訪ねる実験をしたところ、ダイエットをしている人間の方が大きいと判断した。", "effect": "大きい,太い", "method": "", "file_path": "/blog/blog/a2100_fast_mode/how_to_see.md", "page_url": "https://psy.hatenadiary.com/entry/2025/04/09/075621"}, {"key": 7, "type": "Table", "question": "学んだばかりの知識", "actions": [{"text": "", "figure": "Caution"}, {"text": "人には、学んだばかりの知識に関連するものばかり、目につくものである", "figure": "Caution"}], "example": "人には、学んだばかりの知識に関連するものばかり、目につくものである", "effect": "意識する", "method": "", "file_path": "/blog/blog/a2100_fast_mode/how_to_see.md", "page_url": "https://psy.hatenadiary.com/entry/2025/04/09/075621"}, {"key": 8, "type": "Table", "question": "直観の心理と熟考の心理は同時並行で動くため、", "actions": [{"text": "", "figure": "Hammer"}, {"text": "この二つの心理は独立平行で実行されるため、まれにこの二つの心理の結果が対立することがある。国語の選択肢問題で熟考の心理で選んだ選択肢が、直観に反することがある。", "figure": "BpmnTaskMessage"}], "example": "この二つの心理は独立平行で実行されるため、まれにこの二つの心理の結果が対立することがある。国語の選択肢問題で熟考の心理で選んだ選択肢が、直観に反することがある。", "effect": "フリーズする", "method": "", "file_path": "/blog/blog/a2100_fast_mode/0010normal_mode.md", "page_url": "https://psy.hatenadiary.com/entry/2025/04/18/120332"}, {"key": 9, "type": "Table", "question": "未熟なアイドルを応援する", "actions": [{"text": "", "figure": "BpmnTaskMessage"}, {"text": "アイドルを応援する理由は「**自分が支えていると言う実感/誰かの役に立っていると言う実感**」を得たいから。", "figure": "Caution"}], "example": "アイドルを応援する理由は「**自分が支えていると言う実感/誰かの役に立っていると言う実感**」を得たいから。", "effect": "自己効力感,評価する", "method": "", "file_path": "/blog/blog/a1000goal/idol.md", "page_url": "https://psy.hatenadiary.com/entry/2025/08/11/215011"}, {"key": 10, "type": "Table", "question": "承認要求が得られる行動", "actions": [{"text": "", "figure": "BpmnTaskMessage"}, {"text": "ストレートに表現したら反感を買うことがわかっているので、わざわざ迂回する戦略をとり認められようとしている。それだけ、他者から認められることへの執着が強いからである。", "figure": "BpmnTaskMessage"}], "example": "ストレートに表現したら反感を買うことがわかっているので、わざわざ迂回する戦略をとり認められようとしている。それだけ、他者から認められることへの執着が強いからである。", "effect": "評価する", "method": "", "file_path": "/blog/blog/a1000goal/approval_request.md", "page_url": "https://psy.hatenadiary.com/entry/2025/04/18/120315"}, {"key": 11, "type": "Table", "question": "テトリス", "actions": [{"text": "", "figure": "BpmnTaskMessage"}, {"text": "新しい研究によると、20分間のテトリスゲームが、パンデミック中に医療従事者が経験した外傷性記憶の頻度を減少させる可能性があることが示されました。", "figure": "Caution"}], "example": "新しい研究によると、20分間のテトリスゲームが、パンデミック中に医療従事者が経験した外傷性記憶の頻度を減少させる可能性があることが示されました。", "effect": "うつ病", "method": "persol", "file_path": "/blog/blog/1000PERSOL/3000mental_illness/20250423141559Tetris.md", "page_url": "https://psy.hatenadiary.com/entry/2025/04/27/204141"}, {"key": 12, "type": "Table", "question": "糖類", "actions": [{"text": "", "figure": "Hammer"}, {"text": "大規模な研究では、さまざまな種類の飲料がうつ病や不安障害を発症する可能性に関連していることがわかりました。", "figure": "BpmnTaskMessage"}, {"text": "しかし、60祭以上の場合は砂糖または人工的に甘くした飲み物とメンタルヘルスの間に明確な関連はありません。", "figure": "BpmnTaskMessage"}], "example": "大規模な研究では、さまざまな種類の飲料がうつ病や不安障害を発症する可能性に関連していることがわかりました。,しかし、60祭以上の場合は砂糖または人工的に甘くした飲み物とメンタルヘルスの間に明確な関連はありません。", "effect": "うつ病", "method": "persol", "file_path": "/blog/blog/1000PERSOL/3000mental_illness/solo_and_ilinness.md", "page_url": "https://psy.hatenadiary.com/entry/2025/04/12/220051"}, {"key": 13, "type": "Table", "question": "孤独", "actions": [{"text": "", "figure": "BpmnTaskMessage"}, {"text": "新しい研究では、社会的に孤立している個人は、病気になる可能性が高いという結果が出ました。", "figure": "Hammer"}], "example": "新しい研究では、社会的に孤立している個人は、病気になる可能性が高いという結果が出ました。", "effect": "うつ病", "method": "persol", "file_path": "/blog/blog/1000PERSOL/3000mental_illness/solo_and_ilinness.md", "page_url": "https://psy.hatenadiary.com/entry/2025/04/12/220051"}, {"key": 14, "type": "Table", "question": "心臓病", "actions": [{"text": "", "figure": "BpmnTaskMessage"}, {"text": "うつ病は、心臓病の独立した危険因子であり、世界中の障害の主な原因の1つであると予測されています。", "figure": "Hammer"}, {"text": "研究によると、うつ病と心臓病は、強い関係があり、うつ病の有病率は、心臓病の種類によって異なります。", "figure": "BpmnTaskMessage"}], "example": "うつ病は、心臓病の独立した危険因子であり、世界中の障害の主な原因の1つであると予測されています。,研究によると、うつ病と心臓病は、強い関係があり、うつ病の有病率は、心臓病の種類によって異なります。", "effect": "うつ病", "method": "persol", "file_path": "/blog/blog/1000PERSOL/3000mental_illness/solo_and_ilinness.md", "page_url": "https://psy.hatenadiary.com/entry/2025/04/12/220051"}, {"key": 15, "type": "Table", "question": "うつ病", "actions": [{"text": "", "figure": "BpmnTaskMessage"}, {"text": "気分が落ち込んだり、やる気が出なくなったり、様々な身体症状が現れたりする病気", "figure": "Caution"}], "example": "気分が落ち込んだり、やる気が出なくなったり、様々な身体症状が現れたりする病気", "effect": "終了", "method": "persol", "file_path": "/blog/blog/1000PERSOL/3000mental_illness/solo_and_ilinness.md", "page_url": "https://psy.hatenadiary.com/entry/2025/04/12/220051", "category": "Terminal", "text": "うつ病"}, {"key": 16, "type": "Table", "question": "幻覚剤の使用", "actions": [{"text": "", "figure": "Hammer"}, {"text": "幻覚剤の使用を含む救急部門訪問を受けた人は、一般集団と比較して3年以内にSSDを発症する可能性が21倍高い", "figure": "Hammer"}], "example": "幻覚剤の使用を含む救急部門訪問を受けた人は、一般集団と比較して3年以内にSSDを発症する可能性が21倍高い", "effect": "SSD(身体症状症)", "method": "persol", "file_path": "/blog/blog/1000PERSOL/3000mental_illness/drag.md", "page_url": "https://psy.hatenadiary.com/entry/2025/04/04/210935"}, {"key": 17, "type": "Table", "question": "未来", "actions": [{"text": "", "figure": "BpmnTaskMessage"}, {"text": "a", "figure": "Hammer"}], "example": "a", "effect": "終了", "method": "persol", "file_path": "/blog/blog/1000PERSOL/null/main.md", "page_url": "https://psy.hatenadiary.com/entry/2025/02/21/115125", "category": "Terminal", "text": "未来"}, {"key": 18, "type": "Table", "question": "外交性が高い", "actions": [{"text": "", "figure": "Hammer"}, {"text": "a", "figure": "Hammer"}], "example": "a", "effect": "「かかわりを持っている」「他人に注目されている」", "method": "persol", "file_path": "/blog/blog/1000PERSOL/null/main.md", "page_url": "https://psy.hatenadiary.com/entry/2025/02/21/115125"}, {"key": 19, "type": "Table", "question": "開放性が低い", "actions": [{"text": "", "figure": "Caution"}, {"text": "a", "figure": "BpmnTaskMessage"}], "example": "a", "effect": "開放性,支配", "method": "persol", "file_path": "/blog/blog/1000PERSOL/null/main.md", "page_url": "https://psy.hatenadiary.com/entry/2025/02/21/115125"}, {"key": 20, "type": "Table", "question": "開放性が高い", "actions": [{"text": "", "figure": "BpmnTaskMessage"}, {"text": "a", "figure": "BpmnTaskMessage"}], "example": "a", "effect": "開放性", "method": "persol", "file_path": "/blog/blog/1000PERSOL/null/main.md", "page_url": "https://psy.hatenadiary.com/entry/2025/02/21/115125"}, {"key": 21, "type": "Table", "question": "開放性", "actions": [{"text": "", "figure": "BpmnTaskMessage"}, {"text": "a", "figure": "BpmnTaskMessage"}], "example": "a", "effect": "終了", "method": "persol", "file_path": "/blog/blog/1000PERSOL/null/main.md", "page_url": "https://psy.hatenadiary.com/entry/2025/02/21/115125", "category": "Terminal", "text": "開放性"}, {"key": 22, "type": "Table", "question": "外交性が高い", "actions": [{"text": "", "figure": "BpmnTaskMessage"}, {"text": "a", "figure": "Caution"}], "example": "a", "effect": "終了", "method": "persol", "file_path": "/blog/blog/1000PERSOL/null/main.md", "page_url": "https://psy.hatenadiary.com/entry/2025/02/21/115125", "category": "Terminal", "text": "外交性が高い"}, {"key": 23, "type": "Table", "question": "神経症傾向の高い人", "actions": [{"text": "", "figure": "BpmnTaskMessage"}, {"text": "a", "figure": "Hammer"}], "example": "a", "effect": "終了", "method": "persol", "file_path": "/blog/blog/1000PERSOL/null/main.md", "page_url": "https://psy.hatenadiary.com/entry/2025/02/21/115125", "category": "Terminal", "text": "神経症傾向の高い人"}, {"key": 24, "type": "Table", "question": "犯罪者", "actions": [{"text": "", "figure": "BpmnTaskMessage"}, {"text": "a", "figure": "Hammer"}], "example": "a", "effect": "終了", "method": "persol", "file_path": "/blog/blog/1000PERSOL/null/main.md", "page_url": "https://psy.hatenadiary.com/entry/2025/02/21/115125", "category": "Terminal", "text": "犯罪者"}, {"key": 25, "type": "Table", "question": "言語獲得の促進", "actions": [{"text": "", "figure": "Hammer"}, {"text": "a", "figure": "Caution"}], "example": "a", "effect": "終了", "method": "persol", "file_path": "/blog/blog/1000PERSOL/null/main.md", "page_url": "https://psy.hatenadiary.com/entry/2025/02/21/115125", "category": "Terminal", "text": "言語獲得の促進"}, {"key": 26, "type": "Table", "question": "傾聴の促進", "actions": [{"text": "", "figure": "BpmnTaskMessage"}, {"text": "a", "figure": "BpmnTaskMessage"}], "example": "a", "effect": "終了", "method": "persol", "file_path": "/blog/blog/1000PERSOL/null/main.md", "page_url": "https://psy.hatenadiary.com/entry/2025/02/21/115125", "category": "Terminal", "text": "傾聴の促進"}, {"key": 27, "type": "Table", "question": "SSD(身体症状症)", "actions": [{"text": "", "figure": "Caution"}, {"text": "a", "figure": "Hammer"}], "example": "a", "effect": "終了", "method": "persol", "file_path": "/blog/blog/1000PERSOL/null/main.md", "page_url": "https://psy.hatenadiary.com/entry/2025/02/21/115125", "category": "Terminal", "text": "SSD(身体症状症)"}, {"key": 28, "type": "Table", "question": "真面目", "actions": [{"text": "", "figure": "Hammer"}, {"text": "a", "figure": "BpmnTaskMessage"}], "example": "a", "effect": "終了", "method": "persol", "file_path": "/blog/blog/1000PERSOL/null/main.md", "page_url": "https://psy.hatenadiary.com/entry/2025/02/21/115125", "category": "Terminal", "text": "真面目"}, {"key": 29, "type": "Table", "question": "共感", "actions": [{"text": "", "figure": "Hammer"}, {"text": "a", "figure": "BpmnTaskMessage"}], "example": "a", "effect": "終了", "method": "persol", "file_path": "/blog/blog/1000PERSOL/null/main.md", "page_url": "https://psy.hatenadiary.com/entry/2025/02/21/115125", "category": "Terminal", "text": "共感"}, {"key": 30, "type": "Table", "question": "痛み", "actions": [{"text": "", "figure": "Hammer"}, {"text": "げっ歯類では情動伝染（他個体の情動表出を観察した個体に同様の情動が惹起される現象）や，1）", "figure": "Hammer"}, {"text": "痛みの社会的伝達（痛がる他個体を観察した個体が痛覚過敏にな現象）2）などの共感的反応が認められる．", "figure": "Hammer"}], "example": "げっ歯類では情動伝染（他個体の情動表出を観察した個体に同様の情動が惹起される現象）や，1）,痛みの社会的伝達（痛がる他個体を観察した個体が痛覚過敏にな現象）2）などの共感的反応が認められる．", "effect": "共感", "method": "persol", "file_path": "/blog/blog/1000PERSOL/1800brain/position.md", "page_url": "https://psy.hatenadiary.com/entry/2025/02/09/211337"}, {"key": 31, "type": "Table", "question": "ホモ・デリンクエンス", "actions": [{"text": "原始人の遺伝的特徴が隔世遺伝によって再現した原始的（先祖返り）又は退行的な起源を持つ複数の身体的異常の発現", "figure": "Hammer"}, {"text": "犯罪者はこうした退行的隔世遺伝が生じた、人類の下等な段階の甦り、人類の一変種「ホモ・デリンクエンス（犯罪人）」という説", "figure": "BpmnTaskMessage"}, {"text": "小さな脳", "figure": "Hammer"}, {"text": "厚い頭蓋骨", "figure": "BpmnTaskMessage"}, {"text": "大きな顎、顎の前方への突出", "figure": "Caution"}, {"text": "低い額", "figure": "Caution"}, {"text": "高い頬骨", "figure": "Caution"}, {"text": "平らな鼻、または上向きの鼻", "figure": "Hammer"}, {"text": "取っ手のような形をした耳", "figure": "Caution"}, {"text": "鷹のような鼻", "figure": "Caution"}, {"text": "肉付きのよい唇", "figure": "BpmnTaskMessage"}, {"text": "異常な歯並び", "figure": "Hammer"}, {"text": "厳しい目つき、泳ぐ目線", "figure": "BpmnTaskMessage"}, {"text": "毛深さ", "figure": "BpmnTaskMessage"}, {"text": "ひげが少ない、またはない", "figure": "Hammer"}, {"text": "下肢に比べて腕が長い", "figure": "Caution"}], "example": "小さな脳,厚い頭蓋骨,大きな顎、顎の前方への突出,低い額,高い頬骨,平らな鼻、または上向きの鼻,取っ手のような形をした耳,鷹のような鼻,肉付きのよい唇,異常な歯並び,厳しい目つき、泳ぐ目線,毛深さ,ひげが少ない、またはない,下肢に比べて腕が長い", "effect": "犯罪者", "method": "persol", "file_path": "/blog/blog/1000PERSOL/1800brain/crime.md", "page_url": "https://psy.hatenadiary.com/entry/2025/02/09/094740"}, {"key": 32, "type": "Table", "question": "白色", "actions": [{"text": "", "figure": "BpmnTaskMessage"}, {"text": "白は純粋さや清潔さを象徴する色です。", "figure": "Hammer"}, {"text": "しかし、「汚してはいけない」という強迫観念を引き起こすこともあります。このような心理状態は、完璧主義や潔癖症と関連する場合があります。", "figure": "Hammer"}], "example": "白は純粋さや清潔さを象徴する色です。,しかし、「汚してはいけない」という強迫観念を引き起こすこともあります。このような心理状態は、完璧主義や潔癖症と関連する場合があります。", "effect": "強迫性障害", "method": "persol", "file_path": "/blog/blog/1000PERSOL/item/color.md", "page_url": "https://psy.hatenadiary.com/entry/2025/04/17/182108"}, {"key": 33, "type": "Table", "question": "灰色", "actions": [{"text": "", "figure": "Hammer"}, {"text": "灰色は粘土のような色で、包み込むような安心感を与えることがあります。この色は中立的で落ち着いた印象を与え、安定感を求める心理を反映していることがあります。", "figure": "Caution"}], "example": "灰色は粘土のような色で、包み込むような安心感を与えることがあります。この色は中立的で落ち着いた印象を与え、安定感を求める心理を反映していることがあります。", "effect": "リラックス状態", "method": "persol", "file_path": "/blog/blog/1000PERSOL/item/color.md", "page_url": "https://psy.hatenadiary.com/entry/2025/04/17/182108"}, {"key": 34, "type": "Table", "question": "青色", "actions": [{"text": "", "figure": "Hammer"}, {"text": "青は二面性を持つ色です。スカイブルーのような明るい青は自然の豊かさを象徴し、リラックスや開放感を与えます。", "figure": "BpmnTaskMessage"}, {"text": "一方で、濃い青は人工的な冷たさを感じさせ、思考的で理性的な傾向を示すことがあります。", "figure": "Caution"}], "example": "青は二面性を持つ色です。スカイブルーのような明るい青は自然の豊かさを象徴し、リラックスや開放感を与えます。,一方で、濃い青は人工的な冷たさを感じさせ、思考的で理性的な傾向を示すことがあります。", "effect": "リラックス,開放性が高い,冷酷", "method": "persol", "file_path": "/blog/blog/1000PERSOL/item/color.md", "page_url": "https://psy.hatenadiary.com/entry/2025/04/17/182108"}, {"key": 35, "type": "Table", "question": "ピンク色", "actions": [{"text": "", "figure": "Caution"}, {"text": "ピンクは情熱的な赤に純粋な白を混ぜた色で、青春の象徴とされています。", "figure": "Hammer"}, {"text": "この色は若々しさや純粋さ、情熱を表現することが多いです。", "figure": "BpmnTaskMessage"}], "example": "ピンクは情熱的な赤に純粋な白を混ぜた色で、青春の象徴とされています。,この色は若々しさや純粋さ、情熱を表現することが多いです。", "effect": "青春,10代から20代", "method": "persol", "file_path": "/blog/blog/1000PERSOL/item/color.md", "page_url": "https://psy.hatenadiary.com/entry/2025/04/17/182108"}, {"key": 36, "type": "Table", "question": "期待に答えようとする", "actions": [{"text": "", "figure": "BpmnTaskMessage"}, {"text": "「ああしなさい。こうしなさい。」「これしちゃダメ、あれしちゃダメ。」と口出しをする母親がいたとします。", "figure": "BpmnTaskMessage"}, {"text": "実は、母親として自信がなかったから過干渉にならなければならなかったのだとしたら、傍に居る子供が感じる気持ちは、母親の不安です。", "figure": "Hammer"}, {"text": "子供の心では、自分が母親の言うことを聞くことで母親が安心するならばと、いい子ほどがんばります。", "figure": "Hammer"}], "example": "「ああしなさい。こうしなさい。」「これしちゃダメ、あれしちゃダメ。」と口出しをする母親がいたとします。,実は、母親として自信がなかったから過干渉にならなければならなかったのだとしたら、傍に居る子供が感じる気持ちは、母親の不安です。,子供の心では、自分が母親の言うことを聞くことで母親が安心するならばと、いい子ほどがんばります。", "effect": "マザーコンプレックス", "method": "persol", "file_path": "/blog/blog/1000PERSOL/1900education/mother_complex.md", "page_url": "https://psy.hatenadiary.com/entry/2025/04/08/193753"}, {"key": 37, "type": "Table", "question": "オタク文化への興味,顔文字", "actions": [{"text": "まずフェイスブック投稿で相関が見受けられたもの", "figure": "Caution"}, {"text": "インターネット、コンピューター", "figure": "BpmnTaskMessage"}, {"text": "アニメ、マンガ、日本の", "figure": "BpmnTaskMessage"}, {"text": "ポケモン、ファイナルファンタジー", "figure": "Hammer"}, {"text": "顔文字(>_<)", "figure": "BpmnTaskMessage"}], "example": "インターネット、コンピューター,アニメ、マンガ、日本の,ポケモン、ファイナルファンタジー,顔文字(>_<)", "effect": "外交性が低い", "method": "persol", "file_path": "/blog/blog/1000PERSOL/0000bigfive/1000extrovertism.md", "page_url": "https://psy.hatenadiary.com/entry/2025/01/27/204535"}, {"key": 38, "type": "Table", "question": "絵文字の使用", "actions": [{"text": "絵文字を使用する場合は外向性が高いという研究結果も出ている", "figure": "BpmnTaskMessage"}, {"text": "👍", "figure": "Hammer"}], "example": "👍", "effect": "外交性が高い", "method": "persol", "file_path": "/blog/blog/1000PERSOL/0000bigfive/1000extrovertism.md", "page_url": "https://psy.hatenadiary.com/entry/2025/01/27/204535"}, {"key": 39, "type": "Table", "question": "所有権の意識", "actions": [{"text": "Facebook投稿での相関があるテキスト", "figure": "BpmnTaskMessage"}, {"text": "「OOしたほうがいい」という肯定的意見よりも「OOしてはいけない」という**ルールで縛る方向性**で意見を出す。", "figure": "BpmnTaskMessage"}, {"text": "あなた", "figure": "Hammer"}, {"text": "あなたの", "figure": "Caution"}, {"text": "してはいけない", "figure": "Caution"}], "example": "あなた,あなたの,してはいけない", "effect": "開放性が低い", "method": "persol", "file_path": "/blog/blog/1000PERSOL/0000bigfive/2000openness.md", "page_url": "https://psy.hatenadiary.com/entry/2025/01/27/204537"}, {"key": 40, "type": "Table", "question": "長男、長女、行政機関のお堅い方", "actions": [{"text": "", "figure": "Hammer"}, {"text": "開放性の低い方々", "figure": "Hammer"}], "example": "開放性の低い方々", "effect": "開放性が低い", "method": "persol", "file_path": "/blog/blog/1000PERSOL/0000bigfive/2000openness.md", "page_url": "https://psy.hatenadiary.com/entry/2025/01/27/204537"}, {"key": 41, "type": "Table", "question": "人文科学、芸術、心理学", "actions": [{"text": "", "figure": "Hammer"}, {"text": "大学において人文科学、芸術、心理学などを専攻する傾向", "figure": "Caution"}, {"text": "職業興味において研究的興味、芸術的興味の傾向", "figure": "Caution"}], "example": "大学において人文科学、芸術、心理学などを専攻する傾向,職業興味において研究的興味、芸術的興味の傾向", "effect": "開放性が高い", "method": "persol", "file_path": "/blog/blog/1000PERSOL/0000bigfive/2000openness.md", "page_url": "https://psy.hatenadiary.com/entry/2025/01/27/204537"}, {"key": 42, "type": "Table", "question": "経済学、工学、法学", "actions": [{"text": "", "figure": "Caution"}, {"text": "大学において経済学、工学、法学を興味を示す", "figure": "Hammer"}], "example": "大学において経済学、工学、法学を興味を示す", "effect": "開放性が低い", "method": "persol", "file_path": "/blog/blog/1000PERSOL/0000bigfive/2000openness.md", "page_url": "https://psy.hatenadiary.com/entry/2025/01/27/204537"}, {"key": 43, "type": "Table", "question": "ネガティブワード", "actions": [{"text": "", "figure": "Hammer"}, {"text": "fucking", "figure": "Caution"}, {"text": "fuck", "figure": "Hammer"}, {"text": "shit", "figure": "BpmnTaskMessage"}, {"text": "crap", "figure": "Caution"}, {"text": "バカ", "figure": "Hammer"}, {"text": "がっかりした", "figure": "Hammer"}, {"text": "うんざり", "figure": "Caution"}, {"text": "病む", "figure": "Caution"}, {"text": "イライラする", "figure": "BpmnTaskMessage"}, {"text": "退屈", "figure": "BpmnTaskMessage"}, {"text": "ひどい", "figure": "Hammer"}, {"text": "鬱", "figure": "Hammer"}, {"text": "寂しい", "figure": "Caution"}, {"text": "独り", "figure": "BpmnTaskMessage"}, {"text": "地獄", "figure": "Caution"}, {"text": "死ぬ", "figure": "BpmnTaskMessage"}, {"text": "嫌い", "figure": "Hammer"}, {"text": "悪夢", "figure": "BpmnTaskMessage"}, {"text": "泣いている", "figure": "BpmnTaskMessage"}, {"text": "xd　>_<　x_x", "figure": "Hammer"}], "example": "fucking,fuck,shit,crap,バカ,がっかりした,うんざり,病む,イライラする,退屈,ひどい,鬱,寂しい,独り,地獄,死ぬ,嫌い,悪夢,泣いている,xd　>_<　x_x", "effect": "神経症傾向の高い人,犯罪者", "method": "persol", "file_path": "/blog/blog/1000PERSOL/0000bigfive/4000neuroticism.md", "page_url": "https://psy.hatenadiary.com/entry/2025/01/27/204541"}, {"key": 44, "type": "Table", "question": "誠実性", "actions": [{"text": "", "figure": "Caution"}, {"text": "誠実性の高い性格とは、一つの仕事をきちんとこなそうとする気持ちや、他人に対する義務を真剣に考えていることを意味している。", "figure": "BpmnTaskMessage"}], "example": "誠実性の高い性格とは、一つの仕事をきちんとこなそうとする気持ちや、他人に対する義務を真剣に考えていることを意味している。", "effect": "真面目", "method": "persol", "file_path": "/blog/blog/1000PERSOL/0000bigfive/5000sincerity.md", "page_url": "https://psy.hatenadiary.com/entry/2025/01/27/204543"}, {"key": 45, "type": "Table", "question": "強迫性障害", "actions": [{"text": "", "figure": "BpmnTaskMessage"}, {"text": "さらに誠実性を高めると、**強迫性障害**（完璧主義）にも繋がる性格である。", "figure": "Hammer"}, {"text": "OCDの強迫行為は、不安や恐怖を軽減するために、無理やり行う、無意味な行動です", "figure": "BpmnTaskMessage"}], "example": "さらに誠実性を高めると、**強迫性障害**（完璧主義）にも繋がる性格である。,OCDの強迫行為は、不安や恐怖を軽減するために、無理やり行う、無意味な行動です", "effect": "誠実性", "method": "persol", "file_path": "/blog/blog/1000PERSOL/0000bigfive/5000sincerity.md", "page_url": "https://psy.hatenadiary.com/entry/2025/01/27/204543"}, {"key": 46, "type": "Table", "question": "計画性が高い", "actions": [{"text": "", "figure": "Caution"}, {"text": "誠実性の高い人は、効率的（英語版）で組織化されており、気楽で無秩序な人とは対照的である。", "figure": "Caution"}], "example": "誠実性の高い人は、効率的（英語版）で組織化されており、気楽で無秩序な人とは対照的である。", "effect": "誠実性", "method": "persol", "file_path": "/blog/blog/1000PERSOL/0000bigfive/5000sincerity.md", "page_url": "https://psy.hatenadiary.com/entry/2025/01/27/204543"}, {"key": 47, "type": "Table", "question": "「準備ができている」", "actions": [{"text": "", "figure": "BpmnTaskMessage"}, {"text": "仕事をしっかりとこなすこと。**そのために準備を怠らないこと**を教訓としている。", "figure": "Hammer"}], "example": "仕事をしっかりとこなすこと。**そのために準備を怠らないこと**を教訓としている。", "effect": "誠実性", "method": "persol", "file_path": "/blog/blog/1000PERSOL/0000bigfive/5000sincerity.md", "page_url": "https://psy.hatenadiary.com/entry/2025/01/27/204543"}, {"key": 48, "type": "Table", "question": "ジムトレーニング", "actions": [{"text": "", "figure": "Hammer"}, {"text": "仕事をしっかりとこなすこと。**そのために準備を怠らないこと**を教訓としている。", "figure": "Caution"}], "example": "仕事をしっかりとこなすこと。**そのために準備を怠らないこと**を教訓としている。", "effect": "誠実性", "method": "persol", "file_path": "/blog/blog/1000PERSOL/0000bigfive/5000sincerity.md", "page_url": "https://psy.hatenadiary.com/entry/2025/01/27/204543"}, {"key": 49, "type": "Table", "question": "使用する言語が異なる", "actions": [{"text": "言語相対性仮説", "figure": "Caution"}, {"text": "母国語となる言語によって語彙や構文法などには偏りがあり、このことが民族的な認知・思考の偏りを支配している", "figure": "BpmnTaskMessage"}, {"text": "母国語が異なる人々が、異なる認知や思考の傾向を持つ", "figure": "Caution"}], "example": "母国語が異なる人々が、異なる認知や思考の傾向を持つ", "effect": "人の思考や認知の変化", "method": "persol", "file_path": "/blog/blog/1000PERSOL/1900education/child/20250225094658.md", "page_url": "https://psy.hatenadiary.com/entry/2025/02/25/150753"}, {"key": 50, "type": "Table", "question": "マザリーズ", "actions": [{"text": "マザリーズが子供の言葉の発達を促進するように働く。母親を始め、大人が乳幼児に向けた、意識するしないにかかわらず自然と口をついて出る、声の調子が高くゆったりとしたリズムの話し方", "figure": "Caution"}, {"text": "母親が、乳幼児に向けた話し方が、子供の言葉の発達を促進する", "figure": "BpmnTaskMessage"}], "example": "母親が、乳幼児に向けた話し方が、子供の言葉の発達を促進する", "effect": "言語獲得の促進,傾聴の促進", "method": "persol", "file_path": "/blog/blog/1000PERSOL/1900education/child/mother.md", "page_url": "https://psy.hatenadiary.com/entry/2025/02/25/150755"}, {"key": 51, "type": "Table", "question": "母親との関係における規定不安", "actions": [{"text": "子供時代の母親との関係における基底不安が神経症の要因となる", "figure": "BpmnTaskMessage"}, {"text": "孤独感や無力感を克服するために、子供時代の母親との関係を振り返る", "figure": "BpmnTaskMessage"}], "example": "孤独感や無力感を克服するために、子供時代の母親との関係を振り返る", "effect": "神経症傾向の高い人", "method": "persol", "file_path": "/blog/blog/1000PERSOL/1900education/child/20250225093701.md", "page_url": "https://psy.hatenadiary.com/entry/2025/02/25/213713"}, {"key": 52, "type": "Table", "question": "少しづつ上手くなるのではなく", "actions": [{"text": "", "figure": "BpmnTaskMessage"}, {"text": "「少しずつ上手くなる」のではなく、「コツを掴むと一気に上手くなる」。練習はそのきっかけを掴むためのもの。100回よりも1", "figure": "BpmnTaskMessage"}, {"text": "000回練習した方が、そのチャンスは増える。努力は、ひらめきを得るためにするんです。", "figure": "Hammer"}], "example": "「少しずつ上手くなる」のではなく、「コツを掴むと一気に上手くなる」。練習はそのきっかけを掴むためのもの。100回よりも1,000回練習した方が、そのチャンスは増える。努力は、ひらめきを得るためにするんです。", "effect": "育成", "method": "", "file_path": "/blog/blog/0000HUMAN/1000education/not_a_little.md", "page_url": "https://psy.hatenadiary.com/entry/2025/04/22/160958"}, {"key": 53, "type": "Table", "question": "意識する", "actions": [{"text": "", "figure": "Hammer"}, {"text": "a", "figure": "BpmnTaskMessage"}], "example": "a", "effect": "終了", "method": "", "file_path": "/blog/blog/0000HUMAN/null/main.md", "page_url": "https://psy.hatenadiary.com/entry/2025/04/13/095056", "category": "Terminal", "text": "意識する"}, {"key": 54, "type": "Table", "question": "大きい", "actions": [{"text": "", "figure": "BpmnTaskMessage"}, {"text": "a", "figure": "BpmnTaskMessage"}], "example": "a", "effect": "終了", "method": "", "file_path": "/blog/blog/0000HUMAN/null/main.md", "page_url": "https://psy.hatenadiary.com/entry/2025/04/13/095056", "category": "Terminal", "text": "大きい"}, {"key": 55, "type": "Table", "question": "太い", "actions": [{"text": "", "figure": "Hammer"}, {"text": "a", "figure": "Hammer"}], "example": "a", "effect": "終了", "method": "", "file_path": "/blog/blog/0000HUMAN/null/main.md", "page_url": "https://psy.hatenadiary.com/entry/2025/04/13/095056", "category": "Terminal", "text": "太い"}, {"key": 56, "type": "Table", "question": "評価する", "actions": [{"text": "", "figure": "BpmnTaskMessage"}, {"text": "a", "figure": "Hammer"}], "example": "a", "effect": "終了", "method": "", "file_path": "/blog/blog/0000HUMAN/null/main.md", "page_url": "https://psy.hatenadiary.com/entry/2025/04/13/095056", "category": "Terminal", "text": "評価する"}, {"key": 57, "type": "Table", "question": "育成", "actions": [{"text": "", "figure": "Caution"}, {"text": "育成", "figure": "Caution"}], "example": "育成", "effect": "終了", "method": "", "file_path": "/blog/blog/0000HUMAN/null/main.md", "page_url": "https://psy.hatenadiary.com/entry/2025/04/13/095056", "category": "Terminal", "text": "育成"}, {"key": 58, "type": "Table", "question": "ラベリングをする", "actions": [{"text": "", "figure": "Caution"}, {"text": "「ＯＯの専門家」", "figure": "Hammer"}, {"text": "あだ名をつける", "figure": "Caution"}], "example": "「ＯＯの専門家」,あだ名をつける", "effect": "自主的な行動の誘発", "method": "write", "file_path": "/blog/blog/5000WRITE/3000negotiation/2200unconscious.md", "page_url": "https://psy.hatenadiary.com/entry/2025/02/15/110419"}, {"key": 59, "type": "Table", "question": "アンカリング", "actions": [{"text": "", "figure": "BpmnTaskMessage"}, {"text": "住居の買い手が最初に到着した住居の価格を基準に考えてしまう", "figure": "BpmnTaskMessage"}], "example": "住居の買い手が最初に到着した住居の価格を基準に考えてしまう", "effect": "数値の誘導", "method": "write", "file_path": "/blog/blog/5000WRITE/3000negotiation/2200unconscious.md", "page_url": "https://psy.hatenadiary.com/entry/2025/02/15/110419"}, {"key": 60, "type": "Table", "question": "初頭効果", "actions": [{"text": "", "figure": "BpmnTaskMessage"}, {"text": "『良い人であり能力が高く、多少の欠点がある』", "figure": "BpmnTaskMessage"}, {"text": "『欠点があり、能力を発揮できない、良くない人』", "figure": "Caution"}, {"text": "同じ項目だが、後述の方が悪い印象を持つ", "figure": "BpmnTaskMessage"}], "example": "『良い人であり能力が高く、多少の欠点がある』,『欠点があり、能力を発揮できない、良くない人』,同じ項目だが、後述の方が悪い印象を持つ", "effect": "回避行動", "method": "write", "file_path": "/blog/blog/5000WRITE/3000negotiation/2200unconscious.md", "page_url": "https://psy.hatenadiary.com/entry/2025/02/15/110419"}, {"key": 61, "type": "Table", "question": "リスクコミュニケーション", "actions": [{"text": "相手の考え方や懸念事項、それに関心の所在を正確に把握すること", "figure": "Caution"}, {"text": "「よろしければこのOOに関する、一番の懸念点を教えていただけませんか？」", "figure": "BpmnTaskMessage"}, {"text": "「もっとも負荷が高い点はどのようなことでしょうか？」", "figure": "Hammer"}], "example": "「よろしければこのOOに関する、一番の懸念点を教えていただけませんか？」,「もっとも負荷が高い点はどのようなことでしょうか？」", "effect": "自主的な行動の誘発,あゆみより,好感度の向上", "method": "write", "file_path": "/blog/blog/5000WRITE/3000negotiation/conspiracy.md", "page_url": "https://psy.hatenadiary.com/entry/2025/02/10/200017"}, {"key": 62, "type": "Table", "question": "「両面提示」+「反論を促す」+「それを反芻」", "actions": [{"text": "", "figure": "Hammer"}, {"text": "「確かに~」", "figure": "BpmnTaskMessage"}], "example": "「確かに~」", "effect": "十分な知識量がある相手を説得", "method": "write", "file_path": "/blog/blog/5000WRITE/3000negotiation/2900influence.md", "page_url": "https://psy.hatenadiary.com/entry/2025/01/27/210452"}, {"key": 63, "type": "Table", "question": "ミラーリング", "actions": [{"text": "", "figure": "BpmnTaskMessage"}, {"text": "呼吸数", "figure": "Hammer"}, {"text": "声の変調", "figure": "Caution"}, {"text": "リズム", "figure": "Hammer"}, {"text": "呼吸の一時停止", "figure": "BpmnTaskMessage"}, {"text": "動きの強さの模倣", "figure": "Caution"}], "example": "呼吸数,声の変調,リズム,呼吸の一時停止,動きの強さの模倣", "effect": "好感度の向上", "method": "write", "file_path": "/blog/blog/5000WRITE/1000selfproduce/2000relationship2.md", "page_url": "https://psy.hatenadiary.com/entry/2025/01/27/210456"}, {"key": 64, "type": "Table", "question": "共通点を見つける", "actions": [{"text": "ラポールの定義は、共通感です", "figure": "BpmnTaskMessage"}, {"text": "人は自分のような人が好きです。したがって、信頼関係を築きたい場合は、共通性を示す必要があります。", "figure": "Hammer"}, {"text": "「戦争の心理学」の中で「相手も同じ人間だ」と想像力を働かせることで、戦闘員の攻撃性が減少したのを確認しました。", "figure": "BpmnTaskMessage"}], "example": "「戦争の心理学」の中で「相手も同じ人間だ」と想像力を働かせることで、戦闘員の攻撃性が減少したのを確認しました。", "effect": "あゆみより", "method": "write", "file_path": "/blog/blog/5000WRITE/1000selfproduce/2000relationship2.md", "page_url": "https://psy.hatenadiary.com/entry/2025/01/27/210456"}, {"key": 65, "type": "Table", "question": "相手の食いつきそうな話題を振る", "actions": [{"text": "", "figure": "Hammer"}, {"text": "若手のエンジニアだったらフロントエンドやペアプロなどイケイケな話が好き", "figure": "Hammer"}, {"text": "ベテランの歴戦の猛者なら「自分がいかにブラックな職場で無茶なやり取りをしたかの思い出」が好き", "figure": "Hammer"}], "example": "若手のエンジニアだったらフロントエンドやペアプロなどイケイケな話が好き,ベテランの歴戦の猛者なら「自分がいかにブラックな職場で無茶なやり取りをしたかの思い出」が好き", "effect": "好感度の向上", "method": "write", "file_path": "/blog/blog/5000WRITE/1000selfproduce/2000relationship.md", "page_url": "https://psy.hatenadiary.com/entry/2025/01/27/210448"}, {"key": 66, "type": "Table", "question": "自主的な行動の誘発", "actions": [{"text": "", "figure": "Caution"}, {"text": "やる気が満ち溢れている状態", "figure": "Hammer"}], "example": "やる気が満ち溢れている状態", "effect": "終了", "method": "write", "file_path": "/blog/blog/5000WRITE/null/main.md", "page_url": "https://psy.hatenadiary.com/entry/2025/02/16/201716", "category": "Terminal", "text": "自主的な行動の誘発"}, {"key": 67, "type": "Table", "question": "同じ行動を取り続ける", "actions": [{"text": "", "figure": "BpmnTaskMessage"}, {"text": "やる気が満ち溢れている状態", "figure": "Hammer"}], "example": "やる気が満ち溢れている状態", "effect": "終了", "method": "write", "file_path": "/blog/blog/5000WRITE/null/main.md", "page_url": "https://psy.hatenadiary.com/entry/2025/02/16/201716", "category": "Terminal", "text": "同じ行動を取り続ける"}, {"key": 68, "type": "Table", "question": "ステレオタイプに一致", "actions": [{"text": "", "figure": "BpmnTaskMessage"}, {"text": "「彼は医者だから医療の知識がすごい」", "figure": "Caution"}], "example": "「彼は医者だから医療の知識がすごい」", "effect": "共通点を見つける", "method": "write", "file_path": "/blog/blog/5000WRITE/null/main.md", "page_url": "https://psy.hatenadiary.com/entry/2025/02/16/201716"}, {"key": 69, "type": "Table", "question": "期待通り", "actions": [{"text": "", "figure": "Caution"}, {"text": "「思った通り」", "figure": "BpmnTaskMessage"}], "example": "「思った通り」", "effect": "終了", "method": "write", "file_path": "/blog/blog/5000WRITE/null/main.md", "page_url": "https://psy.hatenadiary.com/entry/2025/02/16/201716", "category": "Terminal", "text": "期待通り"}, {"key": 70, "type": "Table", "question": "推論機能の誘発", "actions": [{"text": "", "figure": "Hammer"}, {"text": "a", "figure": "BpmnTaskMessage"}], "example": "a", "effect": "終了", "method": "write", "file_path": "/blog/blog/5000WRITE/null/main.md", "page_url": "https://psy.hatenadiary.com/entry/2025/02/16/201716", "category": "Terminal", "text": "推論機能の誘発"}, {"key": 71, "type": "Table", "question": "あゆみより", "actions": [{"text": "", "figure": "Caution"}, {"text": "a", "figure": "Caution"}], "example": "a", "effect": "終了", "method": "write", "file_path": "/blog/blog/5000WRITE/null/main.md", "page_url": "https://psy.hatenadiary.com/entry/2025/02/16/201716", "category": "Terminal", "text": "あゆみより"}, {"key": 72, "type": "Table", "question": "回避行動", "actions": [{"text": "", "figure": "Hammer"}, {"text": "a", "figure": "Hammer"}], "example": "a", "effect": "終了", "method": "write", "file_path": "/blog/blog/5000WRITE/null/main.md", "page_url": "https://psy.hatenadiary.com/entry/2025/02/16/201716", "category": "Terminal", "text": "回避行動"}, {"key": 73, "type": "Table", "question": "促進行動", "actions": [{"text": "", "figure": "BpmnTaskMessage"}, {"text": "a", "figure": "Hammer"}], "example": "a", "effect": "終了", "method": "write", "file_path": "/blog/blog/5000WRITE/null/main.md", "page_url": "https://psy.hatenadiary.com/entry/2025/02/16/201716", "category": "Terminal", "text": "促進行動"}, {"key": 74, "type": "Table", "question": "数値の誘導", "actions": [{"text": "", "figure": "BpmnTaskMessage"}, {"text": "a", "figure": "Caution"}], "example": "a", "effect": "終了", "method": "write", "file_path": "/blog/blog/5000WRITE/null/main.md", "page_url": "https://psy.hatenadiary.com/entry/2025/02/16/201716", "category": "Terminal", "text": "数値の誘導"}, {"key": 75, "type": "Table", "question": "名詞でラベリングする", "actions": [{"text": "", "figure": "Hammer"}, {"text": "「峰岸は芸術家だ」", "figure": "Hammer"}], "example": "「峰岸は芸術家だ」", "effect": "推論機能の誘発", "method": "write", "file_path": "/blog/blog/5000WRITE/2000presentation/noun.md", "page_url": "https://psy.hatenadiary.com/entry/2025/02/15/110417"}, {"key": 76, "type": "Table", "question": "生存率の提示", "actions": [{"text": "", "figure": "Caution"}, {"text": "癌の外科手術の効果について死亡率の代わりに生存率が示された場合、医師が手術を選択する割合は34%増加した", "figure": "Hammer"}], "example": "癌の外科手術の効果について死亡率の代わりに生存率が示された場合、医師が手術を選択する割合は34%増加した", "effect": "促進行動", "method": "write", "file_path": "/blog/blog/5000WRITE/2000presentation/2901influence.md", "page_url": "https://psy.hatenadiary.com/entry/2025/01/27/210454"}, {"key": 77, "type": "Table", "question": "死亡率を提示せよ", "actions": [{"text": "", "figure": "Caution"}, {"text": "「アクションAが仮に成功すると、プロジェクトは正常に戻りますが、25%の確率で失敗します。」", "figure": "Hammer"}], "example": "「アクションAが仮に成功すると、プロジェクトは正常に戻りますが、25%の確率で失敗します。」", "effect": "回避行動", "method": "write", "file_path": "/blog/blog/5000WRITE/2000presentation/2901influence.md", "page_url": "https://psy.hatenadiary.com/entry/2025/01/27/210454"}, {"key": 78, "type": "Table", "question": "あいまいさ回避", "actions": [{"text": "", "figure": "Hammer"}, {"text": "「６０％ぐらいです」", "figure": "Caution"}], "example": "「６０％ぐらいです」", "effect": "回避行動", "method": "write", "file_path": "/blog/blog/5000WRITE/2000presentation/2901influence.md", "page_url": "https://psy.hatenadiary.com/entry/2025/01/27/210454"}, {"key": 79, "type": "Table", "question": "「かかわりを持っている」「他人に注目されている」", "actions": [{"text": "", "figure": "Hammer"}, {"text": "人から手伝いを頼まれ引き受けると2度目以降も断りにくくなる", "figure": "Hammer"}], "example": "人から手伝いを頼まれ引き受けると2度目以降も断りにくくなる", "effect": "一貫性の法則", "method": "write", "file_path": "/blog/blog/5000WRITE/0000base/consistency.md", "page_url": "https://psy.hatenadiary.com/entry/2025/02/11/110343"}, {"key": 80, "type": "Table", "question": "一貫性の法則", "actions": [{"text": "", "figure": "Hammer"}, {"text": "好きな歌手のCDだからという理由だけで買ってしまう", "figure": "Caution"}], "example": "好きな歌手のCDだからという理由だけで買ってしまう", "effect": "同じ行動を取り続ける", "method": "write", "file_path": "/blog/blog/5000WRITE/0000base/consistency.md", "page_url": "https://psy.hatenadiary.com/entry/2025/02/11/110343"}, {"key": 81, "type": "Table", "question": "命令の後の理由付け", "actions": [{"text": "", "figure": "Hammer"}, {"text": "OOさん。ハサミをとっていただけませんが?切りたいものがあるので", "figure": "Hammer"}], "example": "OOさん。ハサミをとっていただけませんが?切りたいものがあるので", "effect": "促進行動", "method": "write", "file_path": "/blog/blog/5000WRITE/0000base/consistency.md", "page_url": "https://psy.hatenadiary.com/entry/2025/02/11/110343"}, {"key": 82, "type": "Table", "question": "「気にしない」", "actions": [{"text": "", "figure": "Hammer"}, {"text": "自分自身を大らかに見せかけようとしている", "figure": "Caution"}], "example": "自分自身を大らかに見せかけようとしている", "effect": "神経症傾向", "method": "read", "file_path": "/blog/blog/3000READ/3000vorcal_read/dont_care.md", "page_url": "https://psy.hatenadiary.com/entry/2025/04/05/084209"}, {"key": 83, "type": "Table", "question": "言語の抽象度が高い", "actions": [{"text": "", "figure": "BpmnTaskMessage"}, {"text": "「優しい、乱暴だ」", "figure": "BpmnTaskMessage"}], "example": "「優しい、乱暴だ」", "effect": "ステレオタイプに一致,期待通り", "method": "read", "file_path": "/blog/blog/3000READ/3000vorcal_read/2000abstract.md", "page_url": "https://psy.hatenadiary.com/entry/2025/02/13/183022"}, {"key": 84, "type": "Table", "question": "「えーと」", "actions": [{"text": "", "figure": "BpmnTaskMessage"}, {"text": "とくに意味のないこのような発話を「有声休止」といいます。有声休止には二つの機能があると言われています。", "figure": "Caution"}, {"text": "文末などの発話の区切りで黙ってしまうと（この現象を「無声休止」といいます）他の人が話し出すきっかけをつくってしまい", "figure": "Caution"}, {"text": "まだ話したいあなたから発言権が移行する可能性が生じます。", "figure": "Caution"}, {"text": "そこであなたは発言権を維持するために有声休止を発するのです", "figure": "Caution"}, {"text": "有声休止には考えをまとめる補助的役割があるというものもあります", "figure": "Caution"}], "example": "とくに意味のないこのような発話を「有声休止」といいます。有声休止には二つの機能があると言われています。,文末などの発話の区切りで黙ってしまうと（この現象を「無声休止」といいます）他の人が話し出すきっかけをつくってしまい,まだ話したいあなたから発言権が移行する可能性が生じます。,そこであなたは発言権を維持するために有声休止を発するのです,有声休止には考えをまとめる補助的役割があるというものもあります", "effect": "混乱", "method": "read", "file_path": "/blog/blog/3000READ/3000vorcal_read/0005_e-ltuto.md", "page_url": "https://psy.hatenadiary.com/entry/2026/03/28/085651"}, {"key": 85, "type": "Table", "question": "話す速度が変わる", "actions": [{"text": "ある人が真の誠意を話すとき、その人は話す速度を変えることはありません。", "figure": "Caution"}, {"text": "ブレア首相が何度も立ち止まり、話す速度が通常よりもはるかに遅いことに注目してください。", "figure": "BpmnTaskMessage"}, {"text": "彼のゆっくりした話し方と長い間の間合いは、おそらく彼が自分の誠実さを誇張しようとしていること、", "figure": "Hammer"}, {"text": "そして結局ダイアナ妃の死が彼にそれほど影響を与えていなかったことを示しているのかもしれない。", "figure": "BpmnTaskMessage"}], "example": "ブレア首相が何度も立ち止まり、話す速度が通常よりもはるかに遅いことに注目してください。,彼のゆっくりした話し方と長い間の間合いは、おそらく彼が自分の誠実さを誇張しようとしていること、,そして結局ダイアナ妃の死が彼にそれほど影響を与えていなかったことを示しているのかもしれない。", "effect": "誠実性の欠如", "method": "read", "file_path": "/blog/blog/3000READ/3000vorcal_read/1100words.md", "page_url": "https://psy.hatenadiary.com/entry/2025/08/06/212743"}, {"key": 86, "type": "Table", "question": "「なんで?」", "actions": [{"text": "「何で？」という口癖を持つ人は、理由と根拠を求める理屈っぽい人です。頭が良くて好奇心旺盛なため、本当のところ、真相、真理が知りたくて、「何で？」と追求してくる", "figure": "Hammer"}, {"text": "「何で？」が口癖の人は、誰に聞いたら答えてくれるのか、しっかりと検討してから質問するようにする必要があるでしょう。", "figure": "BpmnTaskMessage"}, {"text": "「何で？」「何で？」", "figure": "Caution"}], "example": "「何で？」「何で？」", "effect": "配慮の不足,開放性が高い", "method": "read", "file_path": "/blog/blog/3000READ/3000vorcal_read/why.md", "page_url": "https://psy.hatenadiary.com/entry/2025/04/04/192934"}, {"key": 87, "type": "Table", "question": "「あなた」", "actions": [{"text": "", "figure": "Hammer"}, {"text": "子育ても同じく、なんであなたはいつも散らかすのか。", "figure": "Hammer"}, {"text": "なんであなたは出来ないのか。とあなたにすると怒ってしまいがち。", "figure": "Hammer"}, {"text": "こんなに散らかされるとママは悲しい。一緒に片付けようか。", "figure": "Hammer"}, {"text": "など一呼吸おいて私メッセージにすると人間関係がスムーズになるそうです。", "figure": "Caution"}], "example": "子育ても同じく、なんであなたはいつも散らかすのか。,なんであなたは出来ないのか。とあなたにすると怒ってしまいがち。,こんなに散らかされるとママは悲しい。一緒に片付けようか。,など一呼吸おいて私メッセージにすると人間関係がスムーズになるそうです。", "effect": "支配", "method": "read", "file_path": "/blog/blog/3000READ/3000vorcal_read/1000subject.md", "page_url": "https://psy.hatenadiary.com/entry/2025/04/09/075623"}, {"key": 88, "type": "Table", "question": "「私」", "actions": [{"text": "Ｉ（私）を主語にすると、「こうするのがいいと私は思う」となり、支配的な感じが薄れるので、相手は聞く耳を持ちやすくなります。", "figure": "Caution"}, {"text": "「あくまでも自分の意見を伝えているだけ」というスタンスになりますから、「相手が変わるべきだ」という支配欲の落とし穴にはまりにくくなるのです。", "figure": "Hammer"}], "example": "「あくまでも自分の意見を伝えているだけ」というスタンスになりますから、「相手が変わるべきだ」という支配欲の落とし穴にはまりにくくなるのです。", "effect": "好感度の向上", "method": "read", "file_path": "/blog/blog/3000READ/3000vorcal_read/1000subject.md", "page_url": "https://psy.hatenadiary.com/entry/2025/04/09/075623"}, {"key": 89, "type": "Table", "question": "「今、大丈夫ですか」", "actions": [{"text": "相手の時間を大切にし、忙しい時間への配慮ができる人", "figure": "BpmnTaskMessage"}, {"text": "この人は相手の時間を大切にするからこそ、「今、大丈夫ですか」ときちんと確認します", "figure": "Hammer"}, {"text": "また、人には忙しい時間があり、時間が取れないことがあるということもきちんと理解しています", "figure": "Hammer"}, {"text": "ですから、もしかすると今は忙しいかも知れないと配慮することができるのですね。", "figure": "BpmnTaskMessage"}], "example": "この人は相手の時間を大切にするからこそ、「今、大丈夫ですか」ときちんと確認します,また、人には忙しい時間があり、時間が取れないことがあるということもきちんと理解しています,ですから、もしかすると今は忙しいかも知れないと配慮することができるのですね。", "effect": "気配り,多角的な観点", "method": "read", "file_path": "/blog/blog/3000READ/3000vorcal_read/are_you_ok.md", "page_url": "https://psy.hatenadiary.com/entry/2025/04/02/212521"}, {"key": 90, "type": "Table", "question": "瞬きの回数が10秒に1~2回", "actions": [{"text": "", "figure": "BpmnTaskMessage"}, {"text": "6~10の瞬きはリラックスされたフラットな状態", "figure": "Hammer"}], "example": "6~10の瞬きはリラックスされたフラットな状態", "effect": "リラックス状態", "method": "read", "file_path": "/blog/blog/3000READ/3000gesture/1000read_eyes.md", "page_url": "https://note.com/rei_minegishi/n/n59a175545430"}, {"key": 91, "type": "Table", "question": "極端に少ない瞬き", "actions": [{"text": "", "figure": "Hammer"}, {"text": "13人の参加者のうち10人はまばたきの回数が減りましたが、正直に話すとまばたきの頻度が通常に戻りました", "figure": "Hammer"}], "example": "13人の参加者のうち10人はまばたきの回数が減りましたが、正直に話すとまばたきの頻度が通常に戻りました", "effect": "嘘,緊張状態", "method": "read", "file_path": "/blog/blog/3000READ/3000gesture/1000read_eyes.md", "page_url": "https://note.com/rei_minegishi/n/n59a175545430"}, {"key": 92, "type": "Table", "question": "口が少し空いている状態", "actions": [{"text": "人間は、口を開くと、内臓を見せることになります。", "figure": "Hammer"}, {"text": "相手が口を開けている時は、無防備になっている状態です。", "figure": "BpmnTaskMessage"}], "example": "相手が口を開けている時は、無防備になっている状態です。", "effect": "リラックス状態", "method": "read", "file_path": "/blog/blog/3000READ/3000gesture/1000mouse.md", "page_url": "https://qiita.com/minegishirei_v2/items/41606baa240e52082c9c"}, {"key": 93, "type": "Table", "question": "逆Uの口、くちをすくめる", "actions": [{"text": "口をすくめるのは自分の言葉に対する自信のなさ、または無力感", "figure": "BpmnTaskMessage"}, {"text": "ロバート・デ・ニーロがそのポーズを取ることで有名", "figure": "BpmnTaskMessage"}], "example": "ロバート・デ・ニーロがそのポーズを取ることで有名", "effect": "無関係,無力感", "method": "read", "file_path": "/blog/blog/3000READ/3000gesture/1000mouse.md", "page_url": "https://qiita.com/minegishirei_v2/items/41606baa240e52082c9c"}, {"key": 94, "type": "Table", "question": "リラックス状態", "actions": [{"text": "", "figure": "Hammer"}, {"text": "最高のパフォーマンス", "figure": "Hammer"}], "example": "最高のパフォーマンス", "effect": "終了", "method": "read", "file_path": "/blog/blog/3000READ/null/readme.md", "page_url": "https://psy.hatenadiary.com/entry/2025/02/18/163059", "category": "Terminal", "text": "リラックス状態"}, {"key": 95, "type": "Table", "question": "嘘", "actions": [{"text": "", "figure": "Hammer"}, {"text": "嘘をついている状態", "figure": "Hammer"}], "example": "嘘をついている状態", "effect": "終了", "method": "read", "file_path": "/blog/blog/3000READ/null/readme.md", "page_url": "https://psy.hatenadiary.com/entry/2025/02/18/163059", "category": "Terminal", "text": "嘘"}, {"key": 96, "type": "Table", "question": "緊張状態", "actions": [{"text": "", "figure": "Hammer"}, {"text": "緊張している状態", "figure": "Caution"}], "example": "緊張している状態", "effect": "終了", "method": "read", "file_path": "/blog/blog/3000READ/null/readme.md", "page_url": "https://psy.hatenadiary.com/entry/2025/02/18/163059", "category": "Terminal", "text": "緊張状態"}, {"key": 97, "type": "Table", "question": "無関係", "actions": [{"text": "", "figure": "Caution"}, {"text": "緊張している状態", "figure": "Caution"}], "example": "緊張している状態", "effect": "終了", "method": "read", "file_path": "/blog/blog/3000READ/null/readme.md", "page_url": "https://psy.hatenadiary.com/entry/2025/02/18/163059", "category": "Terminal", "text": "無関係"}, {"key": 98, "type": "Table", "question": "無力感", "actions": [{"text": "", "figure": "Hammer"}, {"text": "緊張している状態", "figure": "Hammer"}], "example": "緊張している状態", "effect": "終了", "method": "read", "file_path": "/blog/blog/3000READ/null/readme.md", "page_url": "https://psy.hatenadiary.com/entry/2025/02/18/163059", "category": "Terminal", "text": "無力感"}, {"key": 99, "type": "Table", "question": "好感度の向上", "actions": [{"text": "", "figure": "Caution"}, {"text": "a", "figure": "Hammer"}], "example": "a", "effect": "一貫性の法則", "method": "read", "file_path": "/blog/blog/3000READ/null/readme.md", "page_url": "https://psy.hatenadiary.com/entry/2025/02/18/163059"}, {"key": 100, "type": "Table", "question": "十分な知識量がある相手を説得", "actions": [{"text": "", "figure": "BpmnTaskMessage"}, {"text": "緊張している状態", "figure": "Hammer"}], "example": "緊張している状態", "effect": "終了", "method": "read", "file_path": "/blog/blog/3000READ/null/readme.md", "page_url": "https://psy.hatenadiary.com/entry/2025/02/18/163059", "category": "Terminal", "text": "十分な知識量がある相手を説得"}, {"key": 101, "type": "Table", "question": "配慮の不足", "actions": [{"text": "", "figure": "BpmnTaskMessage"}, {"text": "配慮の不足", "figure": "BpmnTaskMessage"}], "example": "配慮の不足", "effect": "配慮", "method": "read", "file_path": "/blog/blog/3000READ/null/readme.md", "page_url": "https://psy.hatenadiary.com/entry/2025/02/18/163059"}, {"key": 102, "type": "Table", "question": "気配り", "actions": [{"text": "", "figure": "Caution"}, {"text": "気配り", "figure": "Caution"}], "example": "気配り", "effect": "配慮", "method": "read", "file_path": "/blog/blog/3000READ/null/readme.md", "page_url": "https://psy.hatenadiary.com/entry/2025/02/18/163059"}, {"key": 103, "type": "Table", "question": "配慮", "actions": [{"text": "", "figure": "Caution"}, {"text": "配慮", "figure": "Hammer"}], "example": "配慮", "effect": "終了", "method": "read", "file_path": "/blog/blog/3000READ/null/readme.md", "page_url": "https://psy.hatenadiary.com/entry/2025/02/18/163059", "category": "Terminal", "text": "配慮"}, {"key": 104, "type": "Table", "question": "多角的な観点", "actions": [{"text": "", "figure": "BpmnTaskMessage"}, {"text": "多角的な観点", "figure": "Hammer"}], "example": "多角的な観点", "effect": "終了", "method": "read", "file_path": "/blog/blog/3000READ/null/readme.md", "page_url": "https://psy.hatenadiary.com/entry/2025/02/18/163059", "category": "Terminal", "text": "多角的な観点"}, {"key": 105, "type": "Table", "question": "捻くれ者", "actions": [{"text": "", "figure": "BpmnTaskMessage"}, {"text": "捻くれ者", "figure": "Caution"}], "example": "捻くれ者", "effect": "終了", "method": "read", "file_path": "/blog/blog/3000READ/null/readme.md", "page_url": "https://psy.hatenadiary.com/entry/2025/02/18/163059", "category": "Terminal", "text": "捻くれ者"}, {"key": 106, "type": "Table", "question": "支配", "actions": [{"text": "", "figure": "Hammer"}, {"text": "支配", "figure": "Hammer"}], "example": "支配", "effect": "終了", "method": "read", "file_path": "/blog/blog/3000READ/null/readme.md", "page_url": "https://psy.hatenadiary.com/entry/2025/02/18/163059", "category": "Terminal", "text": "支配"}, {"key": 107, "type": "Table", "question": "混乱", "actions": [{"text": "", "figure": "Caution"}, {"text": "混乱", "figure": "Hammer"}], "example": "混乱", "effect": "終了", "method": "read", "file_path": "/blog/blog/3000READ/null/readme.md", "page_url": "https://psy.hatenadiary.com/entry/2025/02/18/163059", "category": "Terminal", "text": "混乱"}, {"key": 108, "type": "Table", "question": "誠実性の欠如", "actions": [{"text": "", "figure": "Hammer"}, {"text": "誠実性の欠如", "figure": "Caution"}], "example": "誠実性の欠如", "effect": "誠実性", "method": "read", "file_path": "/blog/blog/3000READ/null/readme.md", "page_url": "https://psy.hatenadiary.com/entry/2025/02/18/163059"}, {"key": 109, "type": "Table", "question": "右", "actions": [{"text": "", "figure": "Caution"}, {"text": "用紙を2つに分割し左右に分ける時", "figure": "BpmnTaskMessage"}, {"text": "基本的には右が未来", "figure": "Hammer"}, {"text": "左が過去を表す。", "figure": "BpmnTaskMessage"}, {"text": "木が画面全体を使って使われた時の、葉、枝、幹のそれぞれの意味と組み合わせる形で適応される", "figure": "Hammer"}], "example": "用紙を2つに分割し左右に分ける時,基本的には右が未来,左が過去を表す。,木が画面全体を使って使われた時の、葉、枝、幹のそれぞれの意味と組み合わせる形で適応される", "effect": "未来", "method": "read", "file_path": "/blog/blog/3000READ/1000baum/01time_approach.md", "page_url": "https://psy.hatenadiary.com/entry/2025/04/03/170639"}, {"key": 110, "type": "Table", "question": "右上", "actions": [{"text": "", "figure": "BpmnTaskMessage"}, {"text": "木が根を張り幹を伸ばし葉をつけるように木の成長と時間軸も対応している。", "figure": "Caution"}, {"text": "例えば葉っぱにはこれからの未来への期待が現れることもあるし", "figure": "BpmnTaskMessage"}, {"text": "反対に尖った枝には未知の攻撃に対する防衛意識などが現れる", "figure": "Caution"}], "example": "木が根を張り幹を伸ばし葉をつけるように木の成長と時間軸も対応している。,例えば葉っぱにはこれからの未来への期待が現れることもあるし,反対に尖った枝には未知の攻撃に対する防衛意識などが現れる", "effect": "未来", "method": "read", "file_path": "/blog/blog/3000READ/1000baum/01time_approach.md", "page_url": "https://psy.hatenadiary.com/entry/2025/04/03/170639"}], "linkDataArray": [{"from": 0, "to": 109}, {"from": 2, "to": 17}, {"from": 5, "to": 56}, {"from": 6, "to": 54}, {"from": 6, "to": 55}, {"from": 7, "to": 53}, {"from": 9, "to": 56}, {"from": 10, "to": 56}, {"from": 11, "to": 15}, {"from": 12, "to": 15}, {"from": 13, "to": 15}, {"from": 14, "to": 15}, {"from": 16, "to": 27}, {"from": 18, "to": 79}, {"from": 19, "to": 21}, {"from": 19, "to": 106}, {"from": 20, "to": 21}, {"from": 30, "to": 29}, {"from": 31, "to": 24}, {"from": 32, "to": 45}, {"from": 33, "to": 94}, {"from": 34, "to": 20}, {"from": 38, "to": 18}, {"from": 38, "to": 22}, {"from": 39, "to": 19}, {"from": 40, "to": 19}, {"from": 41, "to": 20}, {"from": 42, "to": 19}, {"from": 43, "to": 23}, {"from": 43, "to": 24}, {"from": 44, "to": 28}, {"from": 45, "to": 44}, {"from": 46, "to": 44}, {"from": 47, "to": 44}, {"from": 48, "to": 44}, {"from": 50, "to": 25}, {"from": 50, "to": 26}, {"from": 51, "to": 23}, {"from": 52, "to": 57}, {"from": 58, "to": 66}, {"from": 59, "to": 74}, {"from": 60, "to": 72}, {"from": 61, "to": 66}, {"from": 61, "to": 71}, {"from": 61, "to": 99}, {"from": 62, "to": 100}, {"from": 63, "to": 99}, {"from": 64, "to": 71}, {"from": 65, "to": 99}, {"from": 68, "to": 64}, {"from": 75, "to": 70}, {"from": 76, "to": 73}, {"from": 77, "to": 72}, {"from": 78, "to": 72}, {"from": 79, "to": 80}, {"from": 80, "to": 67}, {"from": 81, "to": 73}, {"from": 83, "to": 68}, {"from": 83, "to": 69}, {"from": 84, "to": 107}, {"from": 85, "to": 108}, {"from": 86, "to": 20}, {"from": 86, "to": 101}, {"from": 87, "to": 106}, {"from": 88, "to": 99}, {"from": 89, "to": 102}, {"from": 89, "to": 104}, {"from": 90, "to": 94}, {"from": 91, "to": 95}, {"from": 91, "to": 96}, {"from": 92, "to": 94}, {"from": 93, "to": 97}, {"from": 93, "to": 98}, {"from": 99, "to": 80}, {"from": 101, "to": 103}, {"from": 102, "to": 103}, {"from": 108, "to": 44}, {"from": 109, "to": 17}, {"from": 110, "to": 17}]}